mcp_server_qdrant/__init__.py
mcp_server_qdrant/main.py
mcp_server_qdrant/mcp_server.py
mcp_server_qdrant/qdrant.py
mcp_server_qdrant/server.py
mcp_server_qdrant/settings.py
mcp_server_qdrant/common/__init__.py
mcp_server_qdrant/common/filters.py
mcp_server_qdrant/common/func_tools.py
mcp_server_qdrant/common/wrap_filters.py
mcp_server_qdrant/embeddings/__init__.py
mcp_server_qdrant/embeddings/base.py
mcp_server_qdrant/embeddings/bedrock.py
mcp_server_qdrant/embeddings/factory.py
mcp_server_qdrant/embeddings/fastembed.py
mcp_server_qdrant/embeddings/types.py
cnry_mcp_server_qdrant-0.8.3.dist-info/METADATA
cnry_mcp_server_qdrant-0.8.3.dist-info/WHEEL
cnry_mcp_server_qdrant-0.8.3.dist-info/entry_points.txt
cnry_mcp_server_qdrant-0.8.3.dist-info/licenses/LICENSE
cnry_mcp_server_qdrant-0.8.3.dist-info/RECORD
